regex_ease/__init__.py
regex_ease/patterns.py
regex_ease/validators.py
regex_ease-0.1.1.dist-info/LICENSE
regex_ease-0.1.1.dist-info/METADATA
regex_ease-0.1.1.dist-info/WHEEL
regex_ease-0.1.1.dist-info/top_level.txt
regex_ease-0.1.1.dist-info/RECORD
